verystable/__init__.py
verystable/bip32.py
verystable/rpc.py
verystable/script.py
verystable/serialization.py
verystable/softforks.py
verystable/wallet.py
verystable/core/__init__.py
verystable/core/address.py
verystable/core/authproxy.py
verystable/core/bdb.py
verystable/core/blockfilter.py
verystable/core/blocktools.py
verystable/core/coverage.py
verystable/core/descriptors.py
verystable/core/ellswift.py
verystable/core/key.py
verystable/core/messages.py
verystable/core/muhash.py
verystable/core/netutil.py
verystable/core/p2p.py
verystable/core/psbt.py
verystable/core/ripemd160.py
verystable/core/script.py
verystable/core/script_util.py
verystable/core/secp256k1.py
verystable/core/segwit_addr.py
verystable/core/siphash.py
verystable/core/socks5.py
verystable/core/test_framework.py
verystable/core/test_node.py
verystable/core/test_shell.py
verystable/core/util.py
verystable/core/wallet.py
verystable/core/wallet_util.py
verystable-25.99.0.dev0.dist-info/METADATA
verystable-25.99.0.dev0.dist-info/WHEEL
verystable-25.99.0.dev0.dist-info/top_level.txt
verystable-25.99.0.dev0.dist-info/RECORD
