Metadata-Version: 2.1
Name: verystable
Version: 25.99.0.dev0
Summary: Tools for experimenting with Bitcoin Core
Requires-Dist: importlib-metadata ; python_version < "3.11"
Provides-Extra: tests
Requires-Dist: pytest ; extra == 'tests'
Requires-Dist: mypy ; extra == 'tests'
Requires-Dist: ruff ; extra == 'tests'
